[
  {
    "drawDate": "2025-11-28",
    "extractedNumbers": [
      6,
      7,
      13,
      39,
      48
    ],
    "specialNumberExtracted": 4,
    "suggestedNumbers": [
      47,
      28,
      60,
      20,
      39
    ],
    "specialNumberSuggested": 4,
    "matchedCount": 1
  },
  {
    "drawDate": "2025-11-25",
    "extractedNumbers": [
      11,
      15,
      31,
      32,
      59
    ],
    "specialNumberExtracted": 18,
    "suggestedNumbers": [
      15,
      47,
      28,
      60,
      20
    ],
    "specialNumberSuggested": 4,
    "matchedCount": 1
  },
  {
    "drawDate": "2025-11-18",
    "extractedNumbers": [
      5,
      10,
      23,
      27,
      30
    ],
    "specialNumberExtracted": 10,
    "suggestedNumbers": [
      15,
      5,
      47,
      28,
      60
    ],
    "specialNumberSuggested": 4,
    "matchedCount": 1
  },
  {
    "drawDate": "2025-11-11",
    "extractedNumbers": [
      10,
      13,
      40,
      42,
      46
    ],
    "specialNumberExtracted": 1,
    "suggestedNumbers": [
      15,
      5,
      46,
      47,
      28
    ],
    "specialNumberSuggested": 4,
    "matchedCount": 1
  },
  {
    "drawDate": "2025-11-07",
    "extractedNumbers": [
      16,
      21,
      23,
      48,
      70
    ],
    "specialNumberExtracted": 5,
    "suggestedNumbers": [
      15,
      5,
      46,
      47,
      16
    ],
    "specialNumberSuggested": 4,
    "matchedCount": 1
  },
  {
    "drawDate": "2025-10-31",
    "extractedNumbers": [
      2,
      24,
      52,
      66,
      68
    ],
    "specialNumberExtracted": 9,
    "suggestedNumbers": [
      15,
      5,
      66,
      46,
      47
    ],
    "specialNumberSuggested": 4,
    "matchedCount": 1
  },
  {
    "drawDate": "2025-10-28",
    "extractedNumbers": [
      2,
      19,
      33,
      53,
      61
    ],
    "specialNumberExtracted": 14,
    "suggestedNumbers": [
      53,
      15,
      5,
      66,
      46
    ],
    "specialNumberSuggested": 4,
    "matchedCount": 1
  },
  {
    "drawDate": "2025-10-24",
    "extractedNumbers": [
      11,
      18,
      31,
      51,
      56
    ],
    "specialNumberExtracted": 24,
    "suggestedNumbers": [
      53,
      15,
      5,
      51,
      66
    ],
    "specialNumberSuggested": 4,
    "matchedCount": 1
  },
  {
    "drawDate": "2025-10-17",
    "extractedNumbers": [
      9,
      21,
      27,
      48,
      56
    ],
    "specialNumberExtracted": 10,
    "suggestedNumbers": [
      53,
      15,
      5,
      51,
      9
    ],
    "specialNumberSuggested": 4,
    "matchedCount": 1
  },
  {
    "drawDate": "2025-10-10",
    "extractedNumbers": [
      3,
      18,
      23,
      32,
      56
    ],
    "specialNumberExtracted": 8,
    "suggestedNumbers": [
      53,
      3,
      15,
      5,
      51
    ],
    "specialNumberSuggested": 4,
    "matchedCount": 1
  },
  {
    "drawDate": "2025-08-29",
    "extractedNumbers": [
      13,
      31,
      32,
      44,
      45
    ],
    "specialNumberExtracted": 21,
    "suggestedNumbers": [
      53,
      3,
      32,
      15,
      5
    ],
    "specialNumberSuggested": 4,
    "matchedCount": 1
  },
  {
    "drawDate": "2025-08-12",
    "extractedNumbers": [
      1,
      8,
      31,
      56,
      67
    ],
    "specialNumberExtracted": 23,
    "suggestedNumbers": [
      53,
      3,
      32,
      1,
      15
    ],
    "specialNumberSuggested": 4,
    "matchedCount": 1
  },
  {
    "drawDate": "2025-08-01",
    "extractedNumbers": [
      18,
      27,
      29,
      33,
      70
    ],
    "specialNumberExtracted": 22,
    "suggestedNumbers": [
      53,
      3,
      32,
      27,
      1
    ],
    "specialNumberSuggested": 4,
    "matchedCount": 1
  },
  {
    "drawDate": "2025-07-29",
    "extractedNumbers": [
      17,
      30,
      34,
      63,
      67
    ],
    "specialNumberExtracted": 11,
    "suggestedNumbers": [
      67,
      53,
      32,
      27,
      1
    ],
    "specialNumberSuggested": 4,
    "matchedCount": 1
  },
  {
    "drawDate": "2025-07-22",
    "extractedNumbers": [
      22,
      41,
      42,
      59,
      69
    ],
    "specialNumberExtracted": 17,
    "suggestedNumbers": [
      67,
      59,
      53,
      32,
      27
    ],
    "specialNumberSuggested": 4,
    "matchedCount": 1
  },
  {
    "drawDate": "2025-06-17",
    "extractedNumbers": [
      16,
      23,
      39,
      46,
      55
    ],
    "specialNumberExtracted": 12,
    "suggestedNumbers": [
      44,
      67,
      59,
      23,
      53
    ],
    "specialNumberSuggested": 12,
    "matchedCount": 1
  },
  {
    "drawDate": "2025-06-06",
    "extractedNumbers": [
      16,
      40,
      54,
      56,
      57
    ],
    "specialNumberExtracted": 3,
    "suggestedNumbers": [
      44,
      67,
      59,
      23,
      54
    ],
    "specialNumberSuggested": 12,
    "matchedCount": 1
  },
  {
    "drawDate": "2025-05-27",
    "extractedNumbers": [
      6,
      28,
      34,
      48,
      62
    ],
    "specialNumberExtracted": 9,
    "suggestedNumbers": [
      44,
      34,
      36,
      67,
      45
    ],
    "specialNumberSuggested": 12,
    "matchedCount": 1
  },
  {
    "drawDate": "2025-05-20",
    "extractedNumbers": [
      18,
      30,
      33,
      55,
      64
    ],
    "specialNumberExtracted": 11,
    "suggestedNumbers": [
      44,
      18,
      34,
      36,
      67
    ],
    "specialNumberSuggested": 12,
    "matchedCount": 1
  },
  {
    "drawDate": "2025-05-02",
    "extractedNumbers": [
      14,
      37,
      40,
      41,
      68
    ],
    "specialNumberExtracted": 2,
    "suggestedNumbers": [
      44,
      18,
      34,
      68,
      36
    ],
    "specialNumberSuggested": 14,
    "matchedCount": 1
  },
  {
    "drawDate": "2025-04-25",
    "extractedNumbers": [
      38,
      40,
      60,
      62,
      70
    ],
    "specialNumberExtracted": 9,
    "suggestedNumbers": [
      40,
      44,
      18,
      34,
      68
    ],
    "specialNumberSuggested": 14,
    "matchedCount": 1
  },
  {
    "drawDate": "2025-04-15",
    "extractedNumbers": [
      6,
      10,
      13,
      24,
      63
    ],
    "specialNumberExtracted": 2,
    "suggestedNumbers": [
      40,
      6,
      44,
      18,
      34
    ],
    "specialNumberSuggested": 14,
    "matchedCount": 1
  },
  {
    "drawDate": "2025-03-25",
    "extractedNumbers": [
      1,
      5,
      17,
      39,
      62
    ],
    "specialNumberExtracted": 8,
    "suggestedNumbers": [
      40,
      6,
      44,
      18,
      5
    ],
    "specialNumberSuggested": 14,
    "matchedCount": 1
  },
  {
    "drawDate": "2025-02-18",
    "extractedNumbers": [
      1,
      20,
      25,
      58,
      61
    ],
    "specialNumberExtracted": 22,
    "suggestedNumbers": [
      15,
      1,
      40,
      6,
      57
    ],
    "specialNumberSuggested": 10,
    "matchedCount": 1
  },
  {
    "drawDate": "2025-02-11",
    "extractedNumbers": [
      7,
      30,
      39,
      41,
      70
    ],
    "specialNumberExtracted": 13,
    "suggestedNumbers": [
      15,
      1,
      40,
      6,
      70
    ],
    "specialNumberSuggested": 10,
    "matchedCount": 1
  },
  {
    "drawDate": "2025-01-31",
    "extractedNumbers": [
      9,
      28,
      48,
      56,
      63
    ],
    "specialNumberExtracted": 2,
    "suggestedNumbers": [
      15,
      63,
      1,
      40,
      6
    ],
    "specialNumberSuggested": 10,
    "matchedCount": 1
  },
  {
    "drawDate": "2025-01-21",
    "extractedNumbers": [
      27,
      30,
      56,
      64,
      65
    ],
    "specialNumberExtracted": 22,
    "suggestedNumbers": [
      15,
      30,
      63,
      1,
      40
    ],
    "specialNumberSuggested": 10,
    "matchedCount": 1
  },
  {
    "drawDate": "2024-12-27",
    "extractedNumbers": [
      3,
      7,
      37,
      49,
      55
    ],
    "specialNumberExtracted": 6,
    "suggestedNumbers": [
      15,
      7,
      30,
      63,
      1
    ],
    "specialNumberSuggested": 10,
    "matchedCount": 1
  },
  {
    "drawDate": "2024-12-10",
    "extractedNumbers": [
      12,
      14,
      26,
      48,
      52
    ],
    "specialNumberExtracted": 21,
    "suggestedNumbers": [
      15,
      7,
      30,
      63,
      14
    ],
    "specialNumberSuggested": 10,
    "matchedCount": 1
  },
  {
    "drawDate": "2024-11-22",
    "extractedNumbers": [
      13,
      20,
      26,
      32,
      65
    ],
    "specialNumberExtracted": 2,
    "suggestedNumbers": [
      13,
      37,
      15,
      67,
      7
    ],
    "specialNumberSuggested": 10,
    "matchedCount": 1
  },
  {
    "drawDate": "2024-11-12",
    "extractedNumbers": [
      18,
      31,
      33,
      64,
      68
    ],
    "specialNumberExtracted": 17,
    "suggestedNumbers": [
      13,
      37,
      15,
      68,
      67
    ],
    "specialNumberSuggested": 10,
    "matchedCount": 1
  },
  {
    "drawDate": "2024-11-05",
    "extractedNumbers": [
      2,
      24,
      25,
      52,
      58
    ],
    "specialNumberExtracted": 9,
    "suggestedNumbers": [
      13,
      37,
      25,
      15,
      68
    ],
    "specialNumberSuggested": 10,
    "matchedCount": 1
  },
  {
    "drawDate": "2024-11-01",
    "extractedNumbers": [
      11,
      22,
      42,
      46,
      51
    ],
    "specialNumberExtracted": 4,
    "suggestedNumbers": [
      13,
      11,
      37,
      25,
      15
    ],
    "specialNumberSuggested": 10,
    "matchedCount": 1
  },
  {
    "drawDate": "2024-10-18",
    "extractedNumbers": [
      4,
      9,
      26,
      39,
      58
    ],
    "specialNumberExtracted": 23,
    "suggestedNumbers": [
      13,
      11,
      37,
      25,
      4
    ],
    "specialNumberSuggested": 10,
    "matchedCount": 1
  },
  {
    "drawDate": "2024-10-04",
    "extractedNumbers": [
      21,
      39,
      42,
      43,
      45
    ],
    "specialNumberExtracted": 3,
    "suggestedNumbers": [
      39,
      13,
      11,
      37,
      25
    ],
    "specialNumberSuggested": 10,
    "matchedCount": 1
  },
  {
    "drawDate": "2024-09-27",
    "extractedNumbers": [
      29,
      46,
      53,
      69,
      70
    ],
    "specialNumberExtracted": 23,
    "suggestedNumbers": [
      39,
      13,
      46,
      11,
      37
    ],
    "specialNumberSuggested": 10,
    "matchedCount": 1
  },
  {
    "drawDate": "2024-09-13",
    "extractedNumbers": [
      21,
      55,
      56,
      57,
      66
    ],
    "specialNumberExtracted": 1,
    "suggestedNumbers": [
      39,
      13,
      46,
      56,
      11
    ],
    "specialNumberSuggested": 10,
    "matchedCount": 1
  },
  {
    "drawDate": "2024-08-20",
    "extractedNumbers": [
      5,
      20,
      26,
      49,
      51
    ],
    "specialNumberExtracted": 24,
    "suggestedNumbers": [
      41,
      20,
      52,
      39,
      43
    ],
    "specialNumberSuggested": 10,
    "matchedCount": 1
  },
  {
    "drawDate": "2024-08-09",
    "extractedNumbers": [
      12,
      32,
      38,
      40,
      57
    ],
    "specialNumberExtracted": 21,
    "suggestedNumbers": [
      41,
      38,
      20,
      52,
      34
    ],
    "specialNumberSuggested": 10,
    "matchedCount": 1
  },
  {
    "drawDate": "2024-08-06",
    "extractedNumbers": [
      23,
      29,
      36,
      61,
      70
    ],
    "specialNumberExtracted": 22,
    "suggestedNumbers": [
      41,
      38,
      29,
      20,
      52
    ],
    "specialNumberSuggested": 10,
    "matchedCount": 1
  },
  {
    "drawDate": "2024-07-23",
    "extractedNumbers": [
      3,
      9,
      14,
      26,
      51
    ],
    "specialNumberExtracted": 21,
    "suggestedNumbers": [
      9,
      41,
      38,
      29,
      20
    ],
    "specialNumberSuggested": 12,
    "matchedCount": 1
  },
  {
    "drawDate": "2024-07-12",
    "extractedNumbers": [
      15,
      35,
      48,
      53,
      68
    ],
    "specialNumberExtracted": 8,
    "suggestedNumbers": [
      9,
      68,
      41,
      38,
      29
    ],
    "specialNumberSuggested": 22,
    "matchedCount": 1
  },
  {
    "drawDate": "2024-07-02",
    "extractedNumbers": [
      4,
      8,
      19,
      31,
      45
    ],
    "specialNumberExtracted": 11,
    "suggestedNumbers": [
      9,
      68,
      41,
      45,
      38
    ],
    "specialNumberSuggested": 22,
    "matchedCount": 1
  },
  {
    "drawDate": "2024-06-28",
    "extractedNumbers": [
      28,
      31,
      33,
      42,
      66
    ],
    "specialNumberExtracted": 24,
    "suggestedNumbers": [
      9,
      42,
      68,
      41,
      45
    ],
    "specialNumberSuggested": 22,
    "matchedCount": 1
  },
  {
    "drawDate": "2024-05-31",
    "extractedNumbers": [
      4,
      11,
      23,
      33,
      49
    ],
    "specialNumberExtracted": 23,
    "suggestedNumbers": [
      9,
      42,
      68,
      4,
      41
    ],
    "specialNumberSuggested": 22,
    "matchedCount": 1
  },
  {
    "drawDate": "2024-05-28",
    "extractedNumbers": [
      12,
      18,
      48,
      57,
      62
    ],
    "specialNumberExtracted": 4,
    "suggestedNumbers": [
      48,
      9,
      42,
      68,
      4
    ],
    "specialNumberSuggested": 22,
    "matchedCount": 1
  },
  {
    "drawDate": "2024-05-21",
    "extractedNumbers": [
      2,
      5,
      8,
      28,
      69
    ],
    "specialNumberExtracted": 14,
    "suggestedNumbers": [
      48,
      9,
      42,
      5,
      68
    ],
    "specialNumberSuggested": 22,
    "matchedCount": 1
  },
  {
    "drawDate": "2024-05-10",
    "extractedNumbers": [
      13,
      22,
      26,
      32,
      65
    ],
    "specialNumberExtracted": 18,
    "suggestedNumbers": [
      48,
      32,
      9,
      42,
      5
    ],
    "specialNumberSuggested": 22,
    "matchedCount": 1
  },
  {
    "drawDate": "2024-05-07",
    "extractedNumbers": [
      26,
      28,
      36,
      63,
      66
    ],
    "specialNumberExtracted": 15,
    "suggestedNumbers": [
      48,
      32,
      28,
      9,
      42
    ],
    "specialNumberSuggested": 22,
    "matchedCount": 1
  },
  {
    "drawDate": "2024-04-26",
    "extractedNumbers": [
      15,
      23,
      53,
      57,
      61
    ],
    "specialNumberExtracted": 9,
    "suggestedNumbers": [
      48,
      32,
      53,
      28,
      9
    ],
    "specialNumberSuggested": 9,
    "matchedCount": 1
  },
  {
    "drawDate": "2024-04-16",
    "extractedNumbers": [
      21,
      26,
      36,
      44,
      59
    ],
    "specialNumberExtracted": 2,
    "suggestedNumbers": [
      48,
      32,
      36,
      53,
      28
    ],
    "specialNumberSuggested": 9,
    "matchedCount": 1
  },
  {
    "drawDate": "2024-04-02",
    "extractedNumbers": [
      10,
      50,
      56,
      60,
      66
    ],
    "specialNumberExtracted": 19,
    "suggestedNumbers": [
      48,
      56,
      63,
      43,
      52
    ],
    "specialNumberSuggested": 19,
    "matchedCount": 1
  },
  {
    "drawDate": "2024-03-26",
    "extractedNumbers": [
      7,
      11,
      22,
      29,
      38
    ],
    "specialNumberExtracted": 4,
    "suggestedNumbers": [
      48,
      56,
      63,
      7,
      43
    ],
    "specialNumberSuggested": 19,
    "matchedCount": 1
  },
  {
    "drawDate": "2024-03-19",
    "extractedNumbers": [
      24,
      46,
      49,
      62,
      66
    ],
    "specialNumberExtracted": 7,
    "suggestedNumbers": [
      48,
      56,
      24,
      63,
      7
    ],
    "specialNumberSuggested": 19,
    "matchedCount": 1
  },
  {
    "drawDate": "2024-03-15",
    "extractedNumbers": [
      13,
      25,
      50,
      51,
      66
    ],
    "specialNumberExtracted": 6,
    "suggestedNumbers": [
      48,
      56,
      51,
      24,
      63
    ],
    "specialNumberSuggested": 19,
    "matchedCount": 1
  },
  {
    "drawDate": "2024-01-19",
    "extractedNumbers": [
      1,
      9,
      16,
      17,
      30
    ],
    "specialNumberExtracted": 17,
    "suggestedNumbers": [
      4,
      48,
      56,
      41,
      1
    ],
    "specialNumberSuggested": 19,
    "matchedCount": 1
  },
  {
    "drawDate": "2024-01-12",
    "extractedNumbers": [
      19,
      34,
      35,
      45,
      67
    ],
    "specialNumberExtracted": 7,
    "suggestedNumbers": [
      4,
      34,
      48,
      56,
      41
    ],
    "specialNumberSuggested": 19,
    "matchedCount": 1
  },
  {
    "drawDate": "2023-12-19",
    "extractedNumbers": [
      17,
      26,
      50,
      58,
      61
    ],
    "specialNumberExtracted": 11,
    "suggestedNumbers": [
      58,
      4,
      34,
      48,
      56
    ],
    "specialNumberSuggested": 10,
    "matchedCount": 1
  },
  {
    "drawDate": "2023-12-15",
    "extractedNumbers": [
      10,
      20,
      28,
      40,
      54
    ],
    "specialNumberExtracted": 12,
    "suggestedNumbers": [
      58,
      4,
      34,
      48,
      28
    ],
    "specialNumberSuggested": 10,
    "matchedCount": 1
  },
  {
    "drawDate": "2023-11-28",
    "extractedNumbers": [
      27,
      37,
      42,
      59,
      61
    ],
    "specialNumberExtracted": 11,
    "suggestedNumbers": [
      58,
      27,
      4,
      34,
      48
    ],
    "specialNumberSuggested": 10,
    "matchedCount": 1
  },
  {
    "drawDate": "2023-11-21",
    "extractedNumbers": [
      17,
      22,
      25,
      30,
      38
    ],
    "specialNumberExtracted": 24,
    "suggestedNumbers": [
      58,
      27,
      25,
      4,
      34
    ],
    "specialNumberSuggested": 10,
    "matchedCount": 1
  },
  {
    "drawDate": "2023-11-14",
    "extractedNumbers": [
      29,
      35,
      59,
      61,
      69
    ],
    "specialNumberExtracted": 22,
    "suggestedNumbers": [
      58,
      27,
      25,
      4,
      69
    ],
    "specialNumberSuggested": 10,
    "matchedCount": 1
  },
  {
    "drawDate": "2023-10-27",
    "extractedNumbers": [
      11,
      32,
      43,
      57,
      70
    ],
    "specialNumberExtracted": 6,
    "suggestedNumbers": [
      58,
      27,
      25,
      70,
      4
    ],
    "specialNumberSuggested": 10,
    "matchedCount": 1
  },
  {
    "drawDate": "2023-10-24",
    "extractedNumbers": [
      16,
      20,
      30,
      54,
      59
    ],
    "specialNumberExtracted": 7,
    "suggestedNumbers": [
      58,
      27,
      25,
      70,
      16
    ],
    "specialNumberSuggested": 10,
    "matchedCount": 1
  },
  {
    "drawDate": "2023-10-03",
    "extractedNumbers": [
      3,
      19,
      32,
      39,
      59
    ],
    "specialNumberExtracted": 24,
    "suggestedNumbers": [
      58,
      59,
      7,
      49,
      27
    ],
    "specialNumberSuggested": 10,
    "matchedCount": 1
  },
  {
    "drawDate": "2023-09-12",
    "extractedNumbers": [
      2,
      14,
      21,
      42,
      67
    ],
    "specialNumberExtracted": 18,
    "suggestedNumbers": [
      58,
      59,
      14,
      7,
      49
    ],
    "specialNumberSuggested": 10,
    "matchedCount": 1
  },
  {
    "drawDate": "2023-08-22",
    "extractedNumbers": [
      1,
      12,
      26,
      36,
      50
    ],
    "specialNumberExtracted": 7,
    "suggestedNumbers": [
      58,
      59,
      26,
      7,
      49
    ],
    "specialNumberSuggested": 10,
    "matchedCount": 1
  },
  {
    "drawDate": "2023-08-04",
    "extractedNumbers": [
      11,
      30,
      45,
      52,
      56
    ],
    "specialNumberExtracted": 20,
    "suggestedNumbers": [
      56,
      58,
      59,
      26,
      7
    ],
    "specialNumberSuggested": 10,
    "matchedCount": 1
  },
  {
    "drawDate": "2023-08-01",
    "extractedNumbers": [
      8,
      24,
      30,
      45,
      61
    ],
    "specialNumberExtracted": 12,
    "suggestedNumbers": [
      56,
      58,
      30,
      59,
      26
    ],
    "specialNumberSuggested": 10,
    "matchedCount": 1
  },
  {
    "drawDate": "2023-07-21",
    "extractedNumbers": [
      29,
      40,
      47,
      50,
      57
    ],
    "specialNumberExtracted": 25,
    "suggestedNumbers": [
      56,
      58,
      50,
      30,
      59
    ],
    "specialNumberSuggested": 10,
    "matchedCount": 1
  },
  {
    "drawDate": "2023-06-27",
    "extractedNumbers": [
      8,
      34,
      35,
      41,
      52
    ],
    "specialNumberExtracted": 12,
    "suggestedNumbers": [
      56,
      58,
      50,
      30,
      52
    ],
    "specialNumberSuggested": 3,
    "matchedCount": 1
  },
  {
    "drawDate": "2023-06-16",
    "extractedNumbers": [
      4,
      24,
      34,
      45,
      57
    ],
    "specialNumberExtracted": 19,
    "suggestedNumbers": [
      56,
      58,
      24,
      50,
      30
    ],
    "specialNumberSuggested": 10,
    "matchedCount": 1
  },
  {
    "drawDate": "2023-06-06",
    "extractedNumbers": [
      6,
      12,
      23,
      29,
      57
    ],
    "specialNumberExtracted": 4,
    "suggestedNumbers": [
      56,
      6,
      58,
      24,
      50
    ],
    "specialNumberSuggested": 10,
    "matchedCount": 1
  },
  {
    "drawDate": "2023-05-30",
    "extractedNumbers": [
      13,
      16,
      40,
      64,
      68
    ],
    "specialNumberExtracted": 21,
    "suggestedNumbers": [
      56,
      6,
      13,
      58,
      24
    ],
    "specialNumberSuggested": 10,
    "matchedCount": 1
  },
  {
    "drawDate": "2023-05-23",
    "extractedNumbers": [
      3,
      10,
      22,
      65,
      66
    ],
    "specialNumberExtracted": 19,
    "suggestedNumbers": [
      10,
      56,
      6,
      13,
      58
    ],
    "specialNumberSuggested": 10,
    "matchedCount": 1
  },
  {
    "drawDate": "2023-05-16",
    "extractedNumbers": [
      15,
      34,
      36,
      69,
      70
    ],
    "specialNumberExtracted": 17,
    "suggestedNumbers": [
      10,
      11,
      34,
      5,
      56
    ],
    "specialNumberSuggested": 10,
    "matchedCount": 1
  },
  {
    "drawDate": "2023-04-18",
    "extractedNumbers": [
      7,
      9,
      15,
      19,
      25
    ],
    "specialNumberExtracted": 4,
    "suggestedNumbers": [
      10,
      11,
      34,
      5,
      19
    ],
    "specialNumberSuggested": 10,
    "matchedCount": 1
  },
  {
    "drawDate": "2023-04-14",
    "extractedNumbers": [
      23,
      27,
      41,
      48,
      51
    ],
    "specialNumberExtracted": 22,
    "suggestedNumbers": [
      10,
      11,
      34,
      5,
      48
    ],
    "specialNumberSuggested": 10,
    "matchedCount": 1
  },
  {
    "drawDate": "2023-04-04",
    "extractedNumbers": [
      1,
      37,
      45,
      62,
      64
    ],
    "specialNumberExtracted": 4,
    "suggestedNumbers": [
      10,
      11,
      34,
      5,
      37
    ],
    "specialNumberSuggested": 3,
    "matchedCount": 1
  },
  {
    "drawDate": "2023-03-21",
    "extractedNumbers": [
      1,
      21,
      25,
      27,
      40
    ],
    "specialNumberExtracted": 11,
    "suggestedNumbers": [
      42,
      10,
      27,
      11,
      34
    ],
    "specialNumberSuggested": 15,
    "matchedCount": 1
  },
  {
    "drawDate": "2023-03-17",
    "extractedNumbers": [
      26,
      28,
      29,
      39,
      49
    ],
    "specialNumberExtracted": 25,
    "suggestedNumbers": [
      42,
      10,
      27,
      11,
      26
    ],
    "specialNumberSuggested": 15,
    "matchedCount": 1
  },
  {
    "drawDate": "2023-03-10",
    "extractedNumbers": [
      9,
      20,
      59,
      60,
      63
    ],
    "specialNumberExtracted": 5,
    "suggestedNumbers": [
      42,
      10,
      27,
      60,
      11
    ],
    "specialNumberSuggested": 5,
    "matchedCount": 1
  },
  {
    "drawDate": "2023-02-24",
    "extractedNumbers": [
      2,
      22,
      49,
      65,
      67
    ],
    "specialNumberExtracted": 7,
    "suggestedNumbers": [
      49,
      42,
      10,
      27,
      60
    ],
    "specialNumberSuggested": 5,
    "matchedCount": 1
  },
  {
    "drawDate": "2023-01-17",
    "extractedNumbers": [
      2,
      12,
      18,
      24,
      39
    ],
    "specialNumberExtracted": 18,
    "suggestedNumbers": [
      49,
      42,
      10,
      27,
      12
    ],
    "specialNumberSuggested": 5,
    "matchedCount": 1
  },
  {
    "drawDate": "2023-01-06",
    "extractedNumbers": [
      3,
      20,
      46,
      59,
      63
    ],
    "specialNumberExtracted": 13,
    "suggestedNumbers": [
      49,
      42,
      10,
      63,
      27
    ],
    "specialNumberSuggested": 5,
    "matchedCount": 1
  },
  {
    "drawDate": "2022-12-16",
    "extractedNumbers": [
      8,
      35,
      40,
      53,
      56
    ],
    "specialNumberExtracted": 11,
    "suggestedNumbers": [
      49,
      42,
      56,
      62,
      32
    ],
    "specialNumberSuggested": 5,
    "matchedCount": 1
  },
  {
    "drawDate": "2022-11-15",
    "extractedNumbers": [
      6,
      19,
      28,
      46,
      61
    ],
    "specialNumberExtracted": 18,
    "suggestedNumbers": [
      49,
      19,
      42,
      56,
      62
    ],
    "specialNumberSuggested": 5,
    "matchedCount": 1
  },
  {
    "drawDate": "2022-10-28",
    "extractedNumbers": [
      4,
      18,
      31,
      53,
      69
    ],
    "specialNumberExtracted": 7,
    "suggestedNumbers": [
      49,
      19,
      42,
      56,
      4
    ],
    "specialNumberSuggested": 5,
    "matchedCount": 1
  },
  {
    "drawDate": "2022-10-21",
    "extractedNumbers": [
      34,
      36,
      43,
      45,
      68
    ],
    "specialNumberExtracted": 22,
    "suggestedNumbers": [
      49,
      19,
      34,
      42,
      56
    ],
    "specialNumberSuggested": 5,
    "matchedCount": 1
  },
  {
    "drawDate": "2022-09-23",
    "extractedNumbers": [
      5,
      50,
      53,
      58,
      64
    ],
    "specialNumberExtracted": 22,
    "suggestedNumbers": [
      49,
      19,
      44,
      58,
      22
    ],
    "specialNumberSuggested": 6,
    "matchedCount": 1
  },
  {
    "drawDate": "2022-08-23",
    "extractedNumbers": [
      3,
      5,
      47,
      48,
      67
    ],
    "specialNumberExtracted": 7,
    "suggestedNumbers": [
      39,
      28,
      47,
      52,
      49
    ],
    "specialNumberSuggested": 7,
    "matchedCount": 1
  },
  {
    "drawDate": "2022-08-19",
    "extractedNumbers": [
      12,
      18,
      24,
      46,
      65
    ],
    "specialNumberExtracted": 3,
    "suggestedNumbers": [
      39,
      28,
      47,
      46,
      52
    ],
    "specialNumberSuggested": 7,
    "matchedCount": 1
  },
  {
    "drawDate": "2022-08-12",
    "extractedNumbers": [
      23,
      24,
      50,
      54,
      64
    ],
    "specialNumberExtracted": 3,
    "suggestedNumbers": [
      23,
      39,
      28,
      47,
      46
    ],
    "specialNumberSuggested": 7,
    "matchedCount": 1
  },
  {
    "drawDate": "2022-07-29",
    "extractedNumbers": [
      13,
      36,
      45,
      57,
      67
    ],
    "specialNumberExtracted": 14,
    "suggestedNumbers": [
      67,
      23,
      39,
      28,
      47
    ],
    "specialNumberSuggested": 7,
    "matchedCount": 1
  },
  {
    "drawDate": "2022-07-19",
    "extractedNumbers": [
      2,
      31,
      32,
      37,
      70
    ],
    "specialNumberExtracted": 25,
    "suggestedNumbers": [
      67,
      23,
      39,
      2,
      28
    ],
    "specialNumberSuggested": 7,
    "matchedCount": 1
  },
  {
    "drawDate": "2022-07-15",
    "extractedNumbers": [
      8,
      20,
      26,
      53,
      64
    ],
    "specialNumberExtracted": 15,
    "suggestedNumbers": [
      67,
      23,
      39,
      26,
      2
    ],
    "specialNumberSuggested": 7,
    "matchedCount": 1
  },
  {
    "drawDate": "2022-07-12",
    "extractedNumbers": [
      4,
      7,
      10,
      45,
      64
    ],
    "specialNumberExtracted": 12,
    "suggestedNumbers": [
      10,
      67,
      23,
      39,
      26
    ],
    "specialNumberSuggested": 7,
    "matchedCount": 1
  },
  {
    "drawDate": "2022-07-05",
    "extractedNumbers": [
      27,
      31,
      50,
      51,
      61
    ],
    "specialNumberExtracted": 21,
    "suggestedNumbers": [
      10,
      67,
      23,
      39,
      50
    ],
    "specialNumberSuggested": 7,
    "matchedCount": 1
  },
  {
    "drawDate": "2022-07-01",
    "extractedNumbers": [
      1,
      27,
      29,
      38,
      62
    ],
    "specialNumberExtracted": 12,
    "suggestedNumbers": [
      10,
      67,
      23,
      62,
      39
    ],
    "specialNumberSuggested": 7,
    "matchedCount": 1
  },
  {
    "drawDate": "2022-06-28",
    "extractedNumbers": [
      7,
      12,
      21,
      43,
      55
    ],
    "specialNumberExtracted": 11,
    "suggestedNumbers": [
      10,
      67,
      23,
      55,
      62
    ],
    "specialNumberSuggested": 7,
    "matchedCount": 1
  },
  {
    "drawDate": "2022-06-24",
    "extractedNumbers": [
      1,
      7,
      11,
      25,
      56
    ],
    "specialNumberExtracted": 14,
    "suggestedNumbers": [
      10,
      67,
      1,
      23,
      55
    ],
    "specialNumberSuggested": 7,
    "matchedCount": 1
  },
  {
    "drawDate": "2022-06-17",
    "extractedNumbers": [
      20,
      36,
      53,
      56,
      69
    ],
    "specialNumberExtracted": 16,
    "suggestedNumbers": [
      10,
      67,
      1,
      23,
      56
    ],
    "specialNumberSuggested": 7,
    "matchedCount": 1
  },
  {
    "drawDate": "2022-06-10",
    "extractedNumbers": [
      3,
      12,
      14,
      18,
      32
    ],
    "specialNumberExtracted": 4,
    "suggestedNumbers": [
      10,
      37,
      67,
      1,
      12
    ],
    "specialNumberSuggested": 7,
    "matchedCount": 1
  },
  {
    "drawDate": "2022-05-06",
    "extractedNumbers": [
      16,
      21,
      33,
      52,
      70
    ],
    "specialNumberExtracted": 10,
    "suggestedNumbers": [
      41,
      70,
      10,
      65,
      37
    ],
    "specialNumberSuggested": 7,
    "matchedCount": 1
  },
  {
    "drawDate": "2022-04-29",
    "extractedNumbers": [
      9,
      11,
      34,
      49,
      66
    ],
    "specialNumberExtracted": 15,
    "suggestedNumbers": [
      41,
      70,
      10,
      49,
      65
    ],
    "specialNumberSuggested": 7,
    "matchedCount": 1
  },
  {
    "drawDate": "2022-04-19",
    "extractedNumbers": [
      2,
      9,
      33,
      47,
      53
    ],
    "specialNumberExtracted": 24,
    "suggestedNumbers": [
      41,
      70,
      10,
      49,
      33
    ],
    "specialNumberSuggested": 7,
    "matchedCount": 1
  },
  {
    "drawDate": "2022-04-01",
    "extractedNumbers": [
      26,
      42,
      47,
      48,
      63
    ],
    "specialNumberExtracted": 21,
    "suggestedNumbers": [
      41,
      70,
      10,
      49,
      26
    ],
    "specialNumberSuggested": 7,
    "matchedCount": 1
  },
  {
    "drawDate": "2022-03-25",
    "extractedNumbers": [
      3,
      13,
      42,
      51,
      58
    ],
    "specialNumberExtracted": 17,
    "suggestedNumbers": [
      41,
      51,
      70,
      10,
      49
    ],
    "specialNumberSuggested": 7,
    "matchedCount": 1
  },
  {
    "drawDate": "2022-03-15",
    "extractedNumbers": [
      9,
      14,
      28,
      59,
      60
    ],
    "specialNumberExtracted": 24,
    "suggestedNumbers": [
      41,
      51,
      70,
      10,
      14
    ],
    "specialNumberSuggested": 7,
    "matchedCount": 1
  },
  {
    "drawDate": "2022-03-01",
    "extractedNumbers": [
      18,
      22,
      38,
      39,
      50
    ],
    "specialNumberExtracted": 18,
    "suggestedNumbers": [
      47,
      41,
      51,
      18,
      70
    ],
    "specialNumberSuggested": 7,
    "matchedCount": 1
  },
  {
    "drawDate": "2022-02-18",
    "extractedNumbers": [
      6,
      11,
      50,
      63,
      68
    ],
    "specialNumberExtracted": 17,
    "suggestedNumbers": [
      50,
      47,
      41,
      51,
      18
    ],
    "specialNumberSuggested": 7,
    "matchedCount": 1
  },
  {
    "drawDate": "2022-02-01",
    "extractedNumbers": [
      11,
      24,
      38,
      62,
      66
    ],
    "specialNumberExtracted": 1,
    "suggestedNumbers": [
      50,
      47,
      41,
      51,
      11
    ],
    "specialNumberSuggested": 5,
    "matchedCount": 1
  },
  {
    "drawDate": "2022-01-04",
    "extractedNumbers": [
      4,
      6,
      16,
      21,
      22
    ],
    "specialNumberExtracted": 1,
    "suggestedNumbers": [
      50,
      4,
      47,
      41,
      51
    ],
    "specialNumberSuggested": 5,
    "matchedCount": 1
  },
  {
    "drawDate": "2021-12-31",
    "extractedNumbers": [
      2,
      5,
      30,
      46,
      61
    ],
    "specialNumberExtracted": 8,
    "suggestedNumbers": [
      2,
      50,
      4,
      47,
      41
    ],
    "specialNumberSuggested": 5,
    "matchedCount": 1
  },
  {
    "drawDate": "2021-12-21",
    "extractedNumbers": [
      25,
      31,
      58,
      64,
      67
    ],
    "specialNumberExtracted": 24,
    "suggestedNumbers": [
      2,
      50,
      4,
      67,
      47
    ],
    "specialNumberSuggested": 5,
    "matchedCount": 1
  },
  {
    "drawDate": "2021-12-17",
    "extractedNumbers": [
      21,
      32,
      38,
      48,
      62
    ],
    "specialNumberExtracted": 10,
    "suggestedNumbers": [
      2,
      38,
      50,
      4,
      67
    ],
    "specialNumberSuggested": 5,
    "matchedCount": 1
  },
  {
    "drawDate": "2021-12-10",
    "extractedNumbers": [
      23,
      25,
      40,
      42,
      60
    ],
    "specialNumberExtracted": 8,
    "suggestedNumbers": [
      60,
      33,
      2,
      55,
      38
    ],
    "specialNumberSuggested": 20,
    "matchedCount": 1
  },
  {
    "drawDate": "2021-11-30",
    "extractedNumbers": [
      7,
      8,
      26,
      30,
      39
    ],
    "specialNumberExtracted": 17,
    "suggestedNumbers": [
      60,
      33,
      39,
      2,
      55
    ],
    "specialNumberSuggested": 20,
    "matchedCount": 1
  },
  {
    "drawDate": "2021-11-26",
    "extractedNumbers": [
      7,
      27,
      37,
      42,
      59
    ],
    "specialNumberExtracted": 2,
    "suggestedNumbers": [
      60,
      33,
      37,
      39,
      2
    ],
    "specialNumberSuggested": 2,
    "matchedCount": 1
  },
  {
    "drawDate": "2021-11-19",
    "extractedNumbers": [
      5,
      23,
      52,
      53,
      59
    ],
    "specialNumberExtracted": 18,
    "suggestedNumbers": [
      23,
      60,
      33,
      37,
      39
    ],
    "specialNumberSuggested": 2,
    "matchedCount": 1
  },
  {
    "drawDate": "2021-11-16",
    "extractedNumbers": [
      6,
      22,
      44,
      53,
      65
    ],
    "specialNumberExtracted": 3,
    "suggestedNumbers": [
      23,
      60,
      33,
      22,
      37
    ],
    "specialNumberSuggested": 2,
    "matchedCount": 1
  },
  {
    "drawDate": "2021-11-09",
    "extractedNumbers": [
      9,
      14,
      16,
      26,
      49
    ],
    "specialNumberExtracted": 14,
    "suggestedNumbers": [
      23,
      60,
      49,
      33,
      48
    ],
    "specialNumberSuggested": 2,
    "matchedCount": 1
  },
  {
    "drawDate": "2021-11-02",
    "extractedNumbers": [
      5,
      10,
      26,
      58,
      65
    ],
    "specialNumberExtracted": 9,
    "suggestedNumbers": [
      23,
      60,
      49,
      5,
      33
    ],
    "specialNumberSuggested": 2,
    "matchedCount": 1
  },
  {
    "drawDate": "2021-10-29",
    "extractedNumbers": [
      15,
      26,
      28,
      35,
      45
    ],
    "specialNumberExtracted": 4,
    "suggestedNumbers": [
      28,
      23,
      60,
      49,
      5
    ],
    "specialNumberSuggested": 2,
    "matchedCount": 1
  },
  {
    "drawDate": "2021-10-22",
    "extractedNumbers": [
      9,
      14,
      26,
      29,
      66
    ],
    "specialNumberExtracted": 22,
    "suggestedNumbers": [
      28,
      23,
      60,
      49,
      66
    ],
    "specialNumberSuggested": 2,
    "matchedCount": 1
  },
  {
    "drawDate": "2021-09-07",
    "extractedNumbers": [
      15,
      17,
      25,
      32,
      53
    ],
    "specialNumberExtracted": 12,
    "suggestedNumbers": [
      28,
      23,
      60,
      15,
      49
    ],
    "specialNumberSuggested": 6,
    "matchedCount": 1
  },
  {
    "drawDate": "2021-09-03",
    "extractedNumbers": [
      7,
      10,
      12,
      61,
      65
    ],
    "specialNumberExtracted": 3,
    "suggestedNumbers": [
      12,
      23,
      60,
      15,
      49
    ],
    "specialNumberSuggested": 6,
    "matchedCount": 1
  },
  {
    "drawDate": "2021-08-24",
    "extractedNumbers": [
      17,
      18,
      26,
      52,
      67
    ],
    "specialNumberExtracted": 19,
    "suggestedNumbers": [
      12,
      67,
      23,
      60,
      15
    ],
    "specialNumberSuggested": 6,
    "matchedCount": 1
  },
  {
    "drawDate": "2021-08-17",
    "extractedNumbers": [
      3,
      6,
      16,
      38,
      56
    ],
    "specialNumberExtracted": 24,
    "suggestedNumbers": [
      16,
      12,
      67,
      23,
      60
    ],
    "specialNumberSuggested": 6,
    "matchedCount": 1
  },
  {
    "drawDate": "2021-08-10",
    "extractedNumbers": [
      29,
      45,
      50,
      59,
      62
    ],
    "specialNumberExtracted": 12,
    "suggestedNumbers": [
      16,
      62,
      12,
      67,
      23
    ],
    "specialNumberSuggested": 6,
    "matchedCount": 1
  },
  {
    "drawDate": "2021-07-16",
    "extractedNumbers": [
      24,
      25,
      47,
      52,
      57
    ],
    "specialNumberExtracted": 24,
    "suggestedNumbers": [
      16,
      13,
      2,
      24,
      35
    ],
    "specialNumberSuggested": 6,
    "matchedCount": 1
  },
  {
    "drawDate": "2021-07-09",
    "extractedNumbers": [
      6,
      37,
      39,
      41,
      46
    ],
    "specialNumberExtracted": 17,
    "suggestedNumbers": [
      16,
      13,
      2,
      24,
      37
    ],
    "specialNumberSuggested": 6,
    "matchedCount": 1
  },
  {
    "drawDate": "2021-06-29",
    "extractedNumbers": [
      7,
      38,
      50,
      52,
      69
    ],
    "specialNumberExtracted": 21,
    "suggestedNumbers": [
      16,
      13,
      2,
      24,
      69
    ],
    "specialNumberSuggested": 6,
    "matchedCount": 1
  },
  {
    "drawDate": "2021-06-04",
    "extractedNumbers": [
      4,
      30,
      34,
      41,
      64
    ],
    "specialNumberExtracted": 8,
    "suggestedNumbers": [
      51,
      16,
      59,
      13,
      64
    ],
    "specialNumberSuggested": 1,
    "matchedCount": 1
  },
  {
    "drawDate": "2021-05-28",
    "extractedNumbers": [
      10,
      14,
      20,
      47,
      70
    ],
    "specialNumberExtracted": 15,
    "suggestedNumbers": [
      51,
      16,
      70,
      59,
      13
    ],
    "specialNumberSuggested": 23,
    "matchedCount": 1
  },
  {
    "drawDate": "2021-05-18",
    "extractedNumbers": [
      3,
      5,
      56,
      61,
      66
    ],
    "specialNumberExtracted": 4,
    "suggestedNumbers": [
      61,
      51,
      16,
      70,
      59
    ],
    "specialNumberSuggested": 23,
    "matchedCount": 1
  },
  {
    "drawDate": "2021-05-14",
    "extractedNumbers": [
      3,
      18,
      41,
      44,
      68
    ],
    "specialNumberExtracted": 3,
    "suggestedNumbers": [
      61,
      51,
      3,
      16,
      70
    ],
    "specialNumberSuggested": 23,
    "matchedCount": 1
  },
  {
    "drawDate": "2021-05-11",
    "extractedNumbers": [
      7,
      8,
      20,
      36,
      39
    ],
    "specialNumberExtracted": 22,
    "suggestedNumbers": [
      39,
      61,
      51,
      3,
      16
    ],
    "specialNumberSuggested": 23,
    "matchedCount": 1
  },
  {
    "drawDate": "2021-05-04",
    "extractedNumbers": [
      4,
      27,
      32,
      57,
      63
    ],
    "specialNumberExtracted": 22,
    "suggestedNumbers": [
      63,
      39,
      61,
      51,
      3
    ],
    "specialNumberSuggested": 23,
    "matchedCount": 1
  },
  {
    "drawDate": "2021-04-23",
    "extractedNumbers": [
      4,
      28,
      29,
      30,
      60
    ],
    "specialNumberExtracted": 25,
    "suggestedNumbers": [
      30,
      63,
      39,
      61,
      51
    ],
    "specialNumberSuggested": 23,
    "matchedCount": 1
  },
  {
    "drawDate": "2021-04-20",
    "extractedNumbers": [
      6,
      23,
      43,
      49,
      52
    ],
    "specialNumberExtracted": 5,
    "suggestedNumbers": [
      30,
      63,
      39,
      61,
      43
    ],
    "specialNumberSuggested": 23,
    "matchedCount": 1
  },
  {
    "drawDate": "2021-04-13",
    "extractedNumbers": [
      10,
      15,
      19,
      45,
      68
    ],
    "specialNumberExtracted": 9,
    "suggestedNumbers": [
      30,
      63,
      45,
      39,
      61
    ],
    "specialNumberSuggested": 23,
    "matchedCount": 1
  },
  {
    "drawDate": "2021-04-09",
    "extractedNumbers": [
      22,
      26,
      27,
      58,
      66
    ],
    "specialNumberExtracted": 12,
    "suggestedNumbers": [
      30,
      63,
      22,
      45,
      39
    ],
    "specialNumberSuggested": 23,
    "matchedCount": 1
  },
  {
    "drawDate": "2021-03-12",
    "extractedNumbers": [
      2,
      24,
      25,
      31,
      65
    ],
    "specialNumberExtracted": 18,
    "suggestedNumbers": [
      2,
      30,
      63,
      22,
      41
    ],
    "specialNumberSuggested": 23,
    "matchedCount": 1
  },
  {
    "drawDate": "2021-02-09",
    "extractedNumbers": [
      7,
      18,
      21,
      31,
      40
    ],
    "specialNumberExtracted": 9,
    "suggestedNumbers": [
      2,
      21,
      30,
      63,
      22
    ],
    "specialNumberSuggested": 20,
    "matchedCount": 1
  },
  {
    "drawDate": "2021-02-02",
    "extractedNumbers": [
      13,
      37,
      38,
      40,
      67
    ],
    "specialNumberExtracted": 10,
    "suggestedNumbers": [
      40,
      2,
      21,
      30,
      63
    ],
    "specialNumberSuggested": 20,
    "matchedCount": 1
  },
  {
    "drawDate": "2021-01-12",
    "extractedNumbers": [
      12,
      14,
      26,
      28,
      33
    ],
    "specialNumberExtracted": 9,
    "suggestedNumbers": [
      40,
      2,
      21,
      30,
      12
    ],
    "specialNumberSuggested": 24,
    "matchedCount": 1
  },
  {
    "drawDate": "2020-12-18",
    "extractedNumbers": [
      7,
      15,
      25,
      51,
      60
    ],
    "specialNumberExtracted": 5,
    "suggestedNumbers": [
      51,
      40,
      2,
      21,
      30
    ],
    "specialNumberSuggested": 5,
    "matchedCount": 1
  },
  {
    "drawDate": "2020-12-15",
    "extractedNumbers": [
      1,
      10,
      18,
      20,
      46
    ],
    "specialNumberExtracted": 15,
    "suggestedNumbers": [
      1,
      51,
      40,
      2,
      21
    ],
    "specialNumberSuggested": 5,
    "matchedCount": 1
  },
  {
    "drawDate": "2020-12-01",
    "extractedNumbers": [
      7,
      33,
      53,
      61,
      65
    ],
    "specialNumberExtracted": 14,
    "suggestedNumbers": [
      65,
      1,
      51,
      40,
      2
    ],
    "specialNumberSuggested": 5,
    "matchedCount": 1
  },
  {
    "drawDate": "2020-11-20",
    "extractedNumbers": [
      26,
      33,
      45,
      61,
      68
    ],
    "specialNumberExtracted": 17,
    "suggestedNumbers": [
      65,
      61,
      1,
      51,
      40
    ],
    "specialNumberSuggested": 5,
    "matchedCount": 1
  },
  {
    "drawDate": "2020-11-10",
    "extractedNumbers": [
      23,
      45,
      53,
      58,
      62
    ],
    "specialNumberExtracted": 13,
    "suggestedNumbers": [
      65,
      61,
      1,
      51,
      23
    ],
    "specialNumberSuggested": 5,
    "matchedCount": 1
  },
  {
    "drawDate": "2020-10-23",
    "extractedNumbers": [
      18,
      34,
      44,
      60,
      69
    ],
    "specialNumberExtracted": 22,
    "suggestedNumbers": [
      60,
      65,
      61,
      1,
      51
    ],
    "specialNumberSuggested": 5,
    "matchedCount": 1
  },
  {
    "drawDate": "2020-10-16",
    "extractedNumbers": [
      27,
      32,
      50,
      52,
      57
    ],
    "specialNumberExtracted": 12,
    "suggestedNumbers": [
      60,
      65,
      32,
      61,
      1
    ],
    "specialNumberSuggested": 10,
    "matchedCount": 1
  },
  {
    "drawDate": "2020-09-22",
    "extractedNumbers": [
      36,
      43,
      44,
      55,
      68
    ],
    "specialNumberExtracted": 12,
    "suggestedNumbers": [
      68,
      60,
      65,
      32,
      61
    ],
    "specialNumberSuggested": 16,
    "matchedCount": 1
  },
  {
    "drawDate": "2020-09-08",
    "extractedNumbers": [
      7,
      10,
      15,
      31,
      57
    ],
    "specialNumberExtracted": 21,
    "suggestedNumbers": [
      68,
      60,
      65,
      7,
      32
    ],
    "specialNumberSuggested": 16,
    "matchedCount": 1
  },
  {
    "drawDate": "2020-09-01",
    "extractedNumbers": [
      15,
      25,
      26,
      38,
      47
    ],
    "specialNumberExtracted": 22,
    "suggestedNumbers": [
      38,
      68,
      60,
      65,
      7
    ],
    "specialNumberSuggested": 16,
    "matchedCount": 1
  },
  {
    "drawDate": "2020-08-21",
    "extractedNumbers": [
      11,
      15,
      31,
      42,
      63
    ],
    "specialNumberExtracted": 14,
    "suggestedNumbers": [
      38,
      68,
      60,
      63,
      65
    ],
    "specialNumberSuggested": 16,
    "matchedCount": 1
  },
  {
    "drawDate": "2020-08-18",
    "extractedNumbers": [
      4,
      18,
      26,
      27,
      58
    ],
    "specialNumberExtracted": 23,
    "suggestedNumbers": [
      38,
      68,
      18,
      60,
      63
    ],
    "specialNumberSuggested": 16,
    "matchedCount": 1
  },
  {
    "drawDate": "2020-08-07",
    "extractedNumbers": [
      4,
      44,
      53,
      64,
      70
    ],
    "specialNumberExtracted": 3,
    "suggestedNumbers": [
      4,
      38,
      3,
      68,
      18
    ],
    "specialNumberSuggested": 16,
    "matchedCount": 1
  },
  {
    "drawDate": "2020-08-04",
    "extractedNumbers": [
      2,
      22,
      30,
      42,
      62
    ],
    "specialNumberExtracted": 20,
    "suggestedNumbers": [
      4,
      38,
      2,
      3,
      68
    ],
    "specialNumberSuggested": 16,
    "matchedCount": 1
  },
  {
    "drawDate": "2020-07-17",
    "extractedNumbers": [
      12,
      13,
      21,
      46,
      57
    ],
    "specialNumberExtracted": 21,
    "suggestedNumbers": [
      4,
      12,
      38,
      2,
      3
    ],
    "specialNumberSuggested": 23,
    "matchedCount": 1
  },
  {
    "drawDate": "2020-07-14",
    "extractedNumbers": [
      6,
      26,
      55,
      56,
      64
    ],
    "specialNumberExtracted": 22,
    "suggestedNumbers": [
      4,
      64,
      12,
      38,
      2
    ],
    "specialNumberSuggested": 23,
    "matchedCount": 1
  },
  {
    "drawDate": "2020-07-10",
    "extractedNumbers": [
      10,
      15,
      20,
      49,
      53
    ],
    "specialNumberExtracted": 22,
    "suggestedNumbers": [
      4,
      49,
      64,
      12,
      38
    ],
    "specialNumberSuggested": 23,
    "matchedCount": 1
  },
  {
    "drawDate": "2020-07-07",
    "extractedNumbers": [
      16,
      20,
      25,
      30,
      43
    ],
    "specialNumberExtracted": 18,
    "suggestedNumbers": [
      4,
      49,
      64,
      12,
      43
    ],
    "specialNumberSuggested": 23,
    "matchedCount": 1
  },
  {
    "drawDate": "2020-06-26",
    "extractedNumbers": [
      19,
      33,
      37,
      56,
      57
    ],
    "specialNumberExtracted": 6,
    "suggestedNumbers": [
      4,
      49,
      64,
      56,
      12
    ],
    "specialNumberSuggested": 23,
    "matchedCount": 1
  },
  {
    "drawDate": "2020-06-16",
    "extractedNumbers": [
      21,
      23,
      33,
      35,
      42
    ],
    "specialNumberExtracted": 6,
    "suggestedNumbers": [
      42,
      40,
      4,
      48,
      49
    ],
    "specialNumberSuggested": 23,
    "matchedCount": 1
  },
  {
    "drawDate": "2020-06-12",
    "extractedNumbers": [
      9,
      14,
      57,
      67,
      70
    ],
    "specialNumberExtracted": 2,
    "suggestedNumbers": [
      42,
      40,
      4,
      48,
      14
    ],
    "specialNumberSuggested": 23,
    "matchedCount": 1
  },
  {
    "drawDate": "2020-05-26",
    "extractedNumbers": [
      34,
      52,
      58,
      59,
      62
    ],
    "specialNumberExtracted": 4,
    "suggestedNumbers": [
      26,
      42,
      62,
      40,
      23
    ],
    "specialNumberSuggested": 3,
    "matchedCount": 1
  },
  {
    "drawDate": "2020-05-08",
    "extractedNumbers": [
      5,
      20,
      22,
      61,
      70
    ],
    "specialNumberExtracted": 4,
    "suggestedNumbers": [
      26,
      5,
      42,
      62,
      40
    ],
    "specialNumberSuggested": 3,
    "matchedCount": 1
  },
  {
    "drawDate": "2020-04-28",
    "extractedNumbers": [
      13,
      19,
      53,
      54,
      63
    ],
    "specialNumberExtracted": 17,
    "suggestedNumbers": [
      26,
      5,
      19,
      42,
      66
    ],
    "specialNumberSuggested": 3,
    "matchedCount": 1
  },
  {
    "drawDate": "2020-04-24",
    "extractedNumbers": [
      1,
      27,
      32,
      60,
      67
    ],
    "specialNumberExtracted": 18,
    "suggestedNumbers": [
      1,
      26,
      5,
      19,
      42
    ],
    "specialNumberSuggested": 3,
    "matchedCount": 1
  },
  {
    "drawDate": "2020-04-21",
    "extractedNumbers": [
      13,
      15,
      24,
      67,
      70
    ],
    "specialNumberExtracted": 17,
    "suggestedNumbers": [
      1,
      26,
      5,
      67,
      19
    ],
    "specialNumberSuggested": 3,
    "matchedCount": 1
  },
  {
    "drawDate": "2020-04-07",
    "extractedNumbers": [
      25,
      33,
      43,
      51,
      68
    ],
    "specialNumberExtracted": 20,
    "suggestedNumbers": [
      1,
      26,
      5,
      67,
      68
    ],
    "specialNumberSuggested": 7,
    "matchedCount": 1
  },
  {
    "drawDate": "2020-03-20",
    "extractedNumbers": [
      34,
      35,
      41,
      45,
      54
    ],
    "specialNumberExtracted": 5,
    "suggestedNumbers": [
      1,
      26,
      45,
      5,
      67
    ],
    "specialNumberSuggested": 7,
    "matchedCount": 1
  },
  {
    "drawDate": "2020-03-17",
    "extractedNumbers": [
      20,
      27,
      28,
      58,
      59
    ],
    "specialNumberExtracted": 25,
    "suggestedNumbers": [
      1,
      26,
      45,
      59,
      5
    ],
    "specialNumberSuggested": 7,
    "matchedCount": 1
  },
  {
    "drawDate": "2020-03-06",
    "extractedNumbers": [
      15,
      48,
      56,
      58,
      70
    ],
    "specialNumberExtracted": 4,
    "suggestedNumbers": [
      1,
      26,
      15,
      45,
      59
    ],
    "specialNumberSuggested": 7,
    "matchedCount": 1
  },
  {
    "drawDate": "2020-02-04",
    "extractedNumbers": [
      32,
      48,
      50,
      51,
      64
    ],
    "specialNumberExtracted": 10,
    "suggestedNumbers": [
      32,
      1,
      26,
      15,
      45
    ],
    "specialNumberSuggested": 15,
    "matchedCount": 1
  },
  {
    "drawDate": "2020-01-31",
    "extractedNumbers": [
      28,
      31,
      33,
      57,
      62
    ],
    "specialNumberExtracted": 19,
    "suggestedNumbers": [
      32,
      1,
      57,
      26,
      15
    ],
    "specialNumberSuggested": 15,
    "matchedCount": 1
  },
  {
    "drawDate": "2020-01-28",
    "extractedNumbers": [
      17,
      36,
      47,
      51,
      62
    ],
    "specialNumberExtracted": 21,
    "suggestedNumbers": [
      32,
      1,
      57,
      26,
      62
    ],
    "specialNumberSuggested": 15,
    "matchedCount": 1
  },
  {
    "drawDate": "2020-01-14",
    "extractedNumbers": [
      9,
      11,
      13,
      31,
      47
    ],
    "specialNumberExtracted": 11,
    "suggestedNumbers": [
      32,
      1,
      57,
      26,
      13
    ],
    "specialNumberSuggested": 15,
    "matchedCount": 1
  },
  {
    "drawDate": "2020-01-10",
    "extractedNumbers": [
      17,
      27,
      49,
      51,
      66
    ],
    "specialNumberExtracted": 2,
    "suggestedNumbers": [
      32,
      1,
      57,
      26,
      51
    ],
    "specialNumberSuggested": 15,
    "matchedCount": 1
  },
  {
    "drawDate": "2019-12-27",
    "extractedNumbers": [
      17,
      34,
      40,
      63,
      64
    ],
    "specialNumberExtracted": 24,
    "suggestedNumbers": [
      32,
      64,
      1,
      57,
      26
    ],
    "specialNumberSuggested": 15,
    "matchedCount": 1
  },
  {
    "drawDate": "2019-12-13",
    "extractedNumbers": [
      17,
      21,
      29,
      39,
      56
    ],
    "specialNumberExtracted": 22,
    "suggestedNumbers": [
      32,
      21,
      64,
      1,
      57
    ],
    "specialNumberSuggested": 15,
    "matchedCount": 1
  },
  {
    "drawDate": "2019-12-03",
    "extractedNumbers": [
      23,
      43,
      60,
      63,
      69
    ],
    "specialNumberExtracted": 19,
    "suggestedNumbers": [
      69,
      32,
      21,
      64,
      1
    ],
    "specialNumberSuggested": 15,
    "matchedCount": 1
  },
  {
    "drawDate": "2019-11-26",
    "extractedNumbers": [
      8,
      27,
      29,
      38,
      43
    ],
    "specialNumberExtracted": 13,
    "suggestedNumbers": [
      69,
      29,
      32,
      21,
      64
    ],
    "specialNumberSuggested": 15,
    "matchedCount": 1
  },
  {
    "drawDate": "2019-11-19",
    "extractedNumbers": [
      22,
      43,
      44,
      47,
      66
    ],
    "specialNumberExtracted": 22,
    "suggestedNumbers": [
      69,
      29,
      32,
      66,
      21
    ],
    "specialNumberSuggested": 15,
    "matchedCount": 1
  },
  {
    "drawDate": "2019-11-01",
    "extractedNumbers": [
      9,
      20,
      36,
      41,
      54
    ],
    "specialNumberExtracted": 22,
    "suggestedNumbers": [
      69,
      29,
      32,
      66,
      41
    ],
    "specialNumberSuggested": 15,
    "matchedCount": 1
  },
  {
    "drawDate": "2019-10-18",
    "extractedNumbers": [
      18,
      58,
      60,
      65,
      67
    ],
    "specialNumberExtracted": 20,
    "suggestedNumbers": [
      69,
      29,
      32,
      58,
      66
    ],
    "specialNumberSuggested": 15,
    "matchedCount": 1
  },
  {
    "drawDate": "2019-10-11",
    "extractedNumbers": [
      14,
      22,
      30,
      37,
      60
    ],
    "specialNumberExtracted": 8,
    "suggestedNumbers": [
      69,
      60,
      29,
      32,
      58
    ],
    "specialNumberSuggested": 8,
    "matchedCount": 1
  },
  {
    "drawDate": "2019-08-23",
    "extractedNumbers": [
      11,
      15,
      37,
      54,
      68
    ],
    "specialNumberExtracted": 21,
    "suggestedNumbers": [
      69,
      60,
      29,
      54,
      32
    ],
    "specialNumberSuggested": 8,
    "matchedCount": 1
  },
  {
    "drawDate": "2019-08-13",
    "extractedNumbers": [
      7,
      27,
      31,
      34,
      51
    ],
    "specialNumberExtracted": 5,
    "suggestedNumbers": [
      51,
      69,
      60,
      29,
      54
    ],
    "specialNumberSuggested": 8,
    "matchedCount": 1
  },
  {
    "drawDate": "2019-08-09",
    "extractedNumbers": [
      15,
      53,
      56,
      59,
      63
    ],
    "specialNumberExtracted": 1,
    "suggestedNumbers": [
      51,
      69,
      60,
      15,
      29
    ],
    "specialNumberSuggested": 8,
    "matchedCount": 1
  },
  {
    "drawDate": "2019-06-25",
    "extractedNumbers": [
      24,
      33,
      45,
      47,
      61
    ],
    "specialNumberExtracted": 17,
    "suggestedNumbers": [
      51,
      45,
      69,
      2,
      35
    ],
    "specialNumberSuggested": 1,
    "matchedCount": 1
  },
  {
    "drawDate": "2019-06-21",
    "extractedNumbers": [
      13,
      30,
      36,
      48,
      62
    ],
    "specialNumberExtracted": 18,
    "suggestedNumbers": [
      51,
      45,
      13,
      69,
      2
    ],
    "specialNumberSuggested": 1,
    "matchedCount": 1
  },
  {
    "drawDate": "2019-05-07",
    "extractedNumbers": [
      3,
      6,
      34,
      54,
      63
    ],
    "specialNumberExtracted": 19,
    "suggestedNumbers": [
      6,
      19,
      51,
      45,
      27
    ],
    "specialNumberSuggested": 2,
    "matchedCount": 1
  },
  {
    "drawDate": "2019-04-30",
    "extractedNumbers": [
      24,
      37,
      41,
      61,
      70
    ],
    "specialNumberExtracted": 20,
    "suggestedNumbers": [
      6,
      19,
      51,
      45,
      41
    ],
    "specialNumberSuggested": 2,
    "matchedCount": 1
  },
  {
    "drawDate": "2019-04-26",
    "extractedNumbers": [
      9,
      17,
      23,
      30,
      46
    ],
    "specialNumberExtracted": 10,
    "suggestedNumbers": [
      6,
      19,
      51,
      45,
      23
    ],
    "specialNumberSuggested": 2,
    "matchedCount": 1
  },
  {
    "drawDate": "2019-04-09",
    "extractedNumbers": [
      11,
      22,
      34,
      44,
      58
    ],
    "specialNumberExtracted": 9,
    "suggestedNumbers": [
      6,
      19,
      51,
      11,
      45
    ],
    "specialNumberSuggested": 2,
    "matchedCount": 1
  },
  {
    "drawDate": "2019-04-02",
    "extractedNumbers": [
      33,
      47,
      58,
      59,
      64
    ],
    "specialNumberExtracted": 25,
    "suggestedNumbers": [
      47,
      6,
      19,
      51,
      11
    ],
    "specialNumberSuggested": 2,
    "matchedCount": 1
  },
  {
    "drawDate": "2019-02-19",
    "extractedNumbers": [
      17,
      24,
      34,
      56,
      65
    ],
    "specialNumberExtracted": 3,
    "suggestedNumbers": [
      17,
      55,
      47,
      6,
      19
    ],
    "specialNumberSuggested": 25,
    "matchedCount": 1
  },
  {
    "drawDate": "2019-01-15",
    "extractedNumbers": [
      29,
      52,
      58,
      60,
      62
    ],
    "specialNumberExtracted": 7,
    "suggestedNumbers": [
      58,
      17,
      55,
      47,
      6
    ],
    "specialNumberSuggested": 24,
    "matchedCount": 1
  },
  {
    "drawDate": "2019-01-04",
    "extractedNumbers": [
      21,
      29,
      35,
      54,
      60
    ],
    "specialNumberExtracted": 15,
    "suggestedNumbers": [
      58,
      17,
      55,
      21,
      47
    ],
    "specialNumberSuggested": 24,
    "matchedCount": 1
  },
  {
    "drawDate": "2018-12-14",
    "extractedNumbers": [
      5,
      22,
      26,
      43,
      49
    ],
    "specialNumberExtracted": 23,
    "suggestedNumbers": [
      58,
      17,
      55,
      26,
      21
    ],
    "specialNumberSuggested": 24,
    "matchedCount": 1
  },
  {
    "drawDate": "2018-12-04",
    "extractedNumbers": [
      28,
      31,
      41,
      42,
      50
    ],
    "specialNumberExtracted": 4,
    "suggestedNumbers": [
      58,
      17,
      55,
      50,
      26
    ],
    "specialNumberSuggested": 24,
    "matchedCount": 1
  },
  {
    "drawDate": "2018-11-20",
    "extractedNumbers": [
      10,
      16,
      31,
      42,
      66
    ],
    "specialNumberExtracted": 10,
    "suggestedNumbers": [
      58,
      17,
      55,
      50,
      42
    ],
    "specialNumberSuggested": 24,
    "matchedCount": 1
  },
  {
    "drawDate": "2018-11-16",
    "extractedNumbers": [
      33,
      36,
      63,
      68,
      69
    ],
    "specialNumberExtracted": 16,
    "suggestedNumbers": [
      58,
      36,
      17,
      55,
      50
    ],
    "specialNumberSuggested": 24,
    "matchedCount": 1
  },
  {
    "drawDate": "2018-11-06",
    "extractedNumbers": [
      28,
      34,
      37,
      56,
      69
    ],
    "specialNumberExtracted": 12,
    "suggestedNumbers": [
      58,
      36,
      37,
      17,
      55
    ],
    "specialNumberSuggested": 24,
    "matchedCount": 1
  },
  {
    "drawDate": "2018-10-23",
    "extractedNumbers": [
      5,
      28,
      62,
      65,
      70
    ],
    "specialNumberExtracted": 5,
    "suggestedNumbers": [
      58,
      36,
      5,
      37,
      17
    ],
    "specialNumberSuggested": 5,
    "matchedCount": 1
  },
  {
    "drawDate": "2018-10-19",
    "extractedNumbers": [
      15,
      23,
      53,
      65,
      70
    ],
    "specialNumberExtracted": 7,
    "suggestedNumbers": [
      58,
      53,
      36,
      5,
      37
    ],
    "specialNumberSuggested": 5,
    "matchedCount": 1
  },
  {
    "drawDate": "2018-10-12",
    "extractedNumbers": [
      4,
      24,
      46,
      61,
      70
    ],
    "specialNumberExtracted": 7,
    "suggestedNumbers": [
      58,
      53,
      36,
      5,
      24
    ],
    "specialNumberSuggested": 7,
    "matchedCount": 1
  },
  {
    "drawDate": "2018-09-25",
    "extractedNumbers": [
      8,
      16,
      32,
      48,
      61
    ],
    "specialNumberExtracted": 12,
    "suggestedNumbers": [
      58,
      53,
      36,
      48,
      5
    ],
    "specialNumberSuggested": 15,
    "matchedCount": 1
  },
  {
    "drawDate": "2018-09-21",
    "extractedNumbers": [
      1,
      2,
      11,
      52,
      64
    ],
    "specialNumberExtracted": 9,
    "suggestedNumbers": [
      58,
      53,
      36,
      52,
      48
    ],
    "specialNumberSuggested": 15,
    "matchedCount": 1
  },
  {
    "drawDate": "2018-08-31",
    "extractedNumbers": [
      7,
      18,
      29,
      32,
      45
    ],
    "specialNumberExtracted": 17,
    "suggestedNumbers": [
      43,
      23,
      7,
      58,
      53
    ],
    "specialNumberSuggested": 15,
    "matchedCount": 1
  },
  {
    "drawDate": "2018-08-21",
    "extractedNumbers": [
      14,
      16,
      19,
      38,
      57
    ],
    "specialNumberExtracted": 11,
    "suggestedNumbers": [
      57,
      43,
      23,
      20,
      7
    ],
    "specialNumberSuggested": 15,
    "matchedCount": 1
  },
  {
    "drawDate": "2018-08-17",
    "extractedNumbers": [
      1,
      31,
      32,
      47,
      56
    ],
    "specialNumberExtracted": 3,
    "suggestedNumbers": [
      57,
      43,
      23,
      31,
      20
    ],
    "specialNumberSuggested": 15,
    "matchedCount": 1
  },
  {
    "drawDate": "2018-08-10",
    "extractedNumbers": [
      1,
      3,
      12,
      22,
      42
    ],
    "specialNumberExtracted": 6,
    "suggestedNumbers": [
      57,
      43,
      23,
      42,
      31
    ],
    "specialNumberSuggested": 15,
    "matchedCount": 1
  },
  {
    "drawDate": "2018-08-03",
    "extractedNumbers": [
      9,
      28,
      30,
      54,
      60
    ],
    "specialNumberExtracted": 2,
    "suggestedNumbers": [
      57,
      54,
      43,
      23,
      42
    ],
    "specialNumberSuggested": 15,
    "matchedCount": 1
  },
  {
    "drawDate": "2018-07-31",
    "extractedNumbers": [
      12,
      15,
      35,
      64,
      69
    ],
    "specialNumberExtracted": 9,
    "suggestedNumbers": [
      69,
      57,
      54,
      43,
      23
    ],
    "specialNumberSuggested": 15,
    "matchedCount": 1
  },
  {
    "drawDate": "2018-06-26",
    "extractedNumbers": [
      17,
      25,
      29,
      39,
      60
    ],
    "specialNumberExtracted": 19,
    "suggestedNumbers": [
      69,
      50,
      57,
      60,
      54
    ],
    "specialNumberSuggested": 12,
    "matchedCount": 1
  },
  {
    "drawDate": "2018-06-22",
    "extractedNumbers": [
      2,
      6,
      11,
      27,
      44
    ],
    "specialNumberExtracted": 20,
    "suggestedNumbers": [
      69,
      50,
      27,
      57,
      60
    ],
    "specialNumberSuggested": 12,
    "matchedCount": 1
  },
  {
    "drawDate": "2018-06-15",
    "extractedNumbers": [
      1,
      11,
      37,
      47,
      51
    ],
    "specialNumberExtracted": 6,
    "suggestedNumbers": [
      69,
      50,
      37,
      27,
      57
    ],
    "specialNumberSuggested": 12,
    "matchedCount": 1
  },
  {
    "drawDate": "2018-05-25",
    "extractedNumbers": [
      11,
      14,
      51,
      64,
      68
    ],
    "specialNumberExtracted": 25,
    "suggestedNumbers": [
      68,
      69,
      50,
      22,
      37
    ],
    "specialNumberSuggested": 12,
    "matchedCount": 1
  },
  {
    "drawDate": "2018-05-22",
    "extractedNumbers": [
      16,
      17,
      21,
      36,
      48
    ],
    "specialNumberExtracted": 9,
    "suggestedNumbers": [
      68,
      69,
      50,
      22,
      36
    ],
    "specialNumberSuggested": 12,
    "matchedCount": 1
  },
  {
    "drawDate": "2018-04-27",
    "extractedNumbers": [
      2,
      29,
      38,
      63,
      66
    ],
    "specialNumberExtracted": 11,
    "suggestedNumbers": [
      63,
      68,
      69,
      50,
      22
    ],
    "specialNumberSuggested": 12,
    "matchedCount": 1
  },
  {
    "drawDate": "2018-04-20",
    "extractedNumbers": [
      1,
      15,
      18,
      32,
      45
    ],
    "specialNumberExtracted": 4,
    "suggestedNumbers": [
      63,
      45,
      68,
      69,
      50
    ],
    "specialNumberSuggested": 12,
    "matchedCount": 1
  },
  {
    "drawDate": "2018-03-27",
    "extractedNumbers": [
      7,
      25,
      43,
      56,
      59
    ],
    "specialNumberExtracted": 13,
    "suggestedNumbers": [
      32,
      63,
      45,
      56,
      68
    ],
    "specialNumberSuggested": 12,
    "matchedCount": 1
  },
  {
    "drawDate": "2018-03-06",
    "extractedNumbers": [
      1,
      4,
      26,
      35,
      39
    ],
    "specialNumberExtracted": 22,
    "suggestedNumbers": [
      32,
      63,
      45,
      35,
      56
    ],
    "specialNumberSuggested": 12,
    "matchedCount": 1
  },
  {
    "drawDate": "2018-02-23",
    "extractedNumbers": [
      7,
      11,
      13,
      19,
      58
    ],
    "specialNumberExtracted": 9,
    "suggestedNumbers": [
      32,
      13,
      63,
      45,
      35
    ],
    "specialNumberSuggested": 12,
    "matchedCount": 1
  },
  {
    "drawDate": "2018-02-20",
    "extractedNumbers": [
      17,
      19,
      23,
      24,
      43
    ],
    "specialNumberExtracted": 14,
    "suggestedNumbers": [
      32,
      13,
      19,
      63,
      45
    ],
    "specialNumberSuggested": 12,
    "matchedCount": 1
  },
  {
    "drawDate": "2018-02-13",
    "extractedNumbers": [
      5,
      12,
      15,
      46,
      49
    ],
    "specialNumberExtracted": 1,
    "suggestedNumbers": [
      32,
      5,
      13,
      19,
      63
    ],
    "specialNumberSuggested": 12,
    "matchedCount": 1
  },
  {
    "drawDate": "2018-02-06",
    "extractedNumbers": [
      14,
      17,
      25,
      48,
      58
    ],
    "specialNumberExtracted": 25,
    "suggestedNumbers": [
      48,
      32,
      5,
      13,
      19
    ],
    "specialNumberSuggested": 14,
    "matchedCount": 1
  },
  {
    "drawDate": "2018-01-26",
    "extractedNumbers": [
      10,
      16,
      27,
      38,
      43
    ],
    "specialNumberExtracted": 1,
    "suggestedNumbers": [
      48,
      43,
      32,
      5,
      13
    ],
    "specialNumberSuggested": 4,
    "matchedCount": 1
  },
  {
    "drawDate": "2018-01-19",
    "extractedNumbers": [
      3,
      17,
      23,
      49,
      66
    ],
    "specialNumberExtracted": 23,
    "suggestedNumbers": [
      48,
      43,
      32,
      66,
      5
    ],
    "specialNumberSuggested": 4,
    "matchedCount": 1
  },
  {
    "drawDate": "2018-01-16",
    "extractedNumbers": [
      3,
      11,
      23,
      29,
      59
    ],
    "specialNumberExtracted": 18,
    "suggestedNumbers": [
      48,
      43,
      32,
      11,
      66
    ],
    "specialNumberSuggested": 4,
    "matchedCount": 1
  },
  {
    "drawDate": "2018-01-09",
    "extractedNumbers": [
      16,
      29,
      31,
      65,
      67
    ],
    "specialNumberExtracted": 23,
    "suggestedNumbers": [
      48,
      43,
      29,
      32,
      11
    ],
    "specialNumberSuggested": 4,
    "matchedCount": 1
  },
  {
    "drawDate": "2017-12-22",
    "extractedNumbers": [
      1,
      20,
      30,
      33,
      42
    ],
    "specialNumberExtracted": 16,
    "suggestedNumbers": [
      48,
      43,
      29,
      30,
      32
    ],
    "specialNumberSuggested": 4,
    "matchedCount": 1
  },
  {
    "drawDate": "2017-12-15",
    "extractedNumbers": [
      4,
      12,
      36,
      44,
      57
    ],
    "specialNumberExtracted": 19,
    "suggestedNumbers": [
      48,
      43,
      29,
      30,
      44
    ],
    "specialNumberSuggested": 4,
    "matchedCount": 1
  },
  {
    "drawDate": "2017-12-12",
    "extractedNumbers": [
      8,
      23,
      24,
      25,
      27
    ],
    "specialNumberExtracted": 9,
    "suggestedNumbers": [
      48,
      43,
      8,
      29,
      30
    ],
    "specialNumberSuggested": 4,
    "matchedCount": 1
  },
  {
    "drawDate": "2017-12-01",
    "extractedNumbers": [
      16,
      22,
      40,
      41,
      59
    ],
    "specialNumberExtracted": 8,
    "suggestedNumbers": [
      48,
      59,
      43,
      8,
      29
    ],
    "specialNumberSuggested": 4,
    "matchedCount": 1
  },
  {
    "drawDate": "2017-11-07",
    "extractedNumbers": [
      1,
      54,
      60,
      68,
      69
    ],
    "specialNumberExtracted": 11,
    "suggestedNumbers": [
      68,
      48,
      59,
      43,
      8
    ],
    "specialNumberSuggested": 4,
    "matchedCount": 1
  },
  {
    "drawDate": "2017-11-03",
    "extractedNumbers": [
      10,
      22,
      42,
      61,
      69
    ],
    "specialNumberExtracted": 3,
    "suggestedNumbers": [
      68,
      48,
      59,
      69,
      43
    ],
    "specialNumberSuggested": 4,
    "matchedCount": 1
  },
  {
    "drawDate": "2017-10-17",
    "extractedNumbers": [
      31,
      45,
      49,
      56,
      70
    ],
    "specialNumberExtracted": 11,
    "suggestedNumbers": [
      68,
      48,
      59,
      70,
      69
    ],
    "specialNumberSuggested": 4,
    "matchedCount": 1
  },
  {
    "drawDate": "2017-10-06",
    "extractedNumbers": [
      21,
      33,
      36,
      45,
      56
    ],
    "specialNumberExtracted": 12,
    "suggestedNumbers": [
      62,
      36,
      68,
      48,
      7
    ],
    "specialNumberSuggested": 4,
    "matchedCount": 1
  },
  {
    "drawDate": "2017-09-12",
    "extractedNumbers": [
      26,
      37,
      41,
      54,
      65
    ],
    "specialNumberExtracted": 3,
    "suggestedNumbers": [
      62,
      66,
      36,
      54,
      68
    ],
    "specialNumberSuggested": 4,
    "matchedCount": 1
  },
  {
    "drawDate": "2017-08-25",
    "extractedNumbers": [
      17,
      38,
      42,
      51,
      65
    ],
    "specialNumberExtracted": 11,
    "suggestedNumbers": [
      62,
      66,
      36,
      54,
      65
    ],
    "specialNumberSuggested": 4,
    "matchedCount": 1
  },
  {
    "drawDate": "2017-05-26",
    "extractedNumbers": [
      25,
      26,
      28,
      37,
      56
    ],
    "specialNumberExtracted": 5,
    "suggestedNumbers": [
      52,
      62,
      57,
      66,
      25
    ],
    "specialNumberSuggested": 4,
    "matchedCount": 1
  },
  {
    "drawDate": "2017-05-05",
    "extractedNumbers": [
      4,
      23,
      33,
      47,
      53
    ],
    "specialNumberExtracted": 7,
    "suggestedNumbers": [
      52,
      4,
      62,
      57,
      66
    ],
    "specialNumberSuggested": 4,
    "matchedCount": 1
  },
  {
    "drawDate": "2017-04-25",
    "extractedNumbers": [
      3,
      13,
      33,
      40,
      50
    ],
    "specialNumberExtracted": 2,
    "suggestedNumbers": [
      52,
      4,
      50,
      62,
      57
    ],
    "specialNumberSuggested": 7,
    "matchedCount": 1
  },
  {
    "drawDate": "2017-03-28",
    "extractedNumbers": [
      30,
      33,
      35,
      37,
      46
    ],
    "specialNumberExtracted": 10,
    "suggestedNumbers": [
      52,
      4,
      50,
      62,
      46
    ],
    "specialNumberSuggested": 7,
    "matchedCount": 1
  },
  {
    "drawDate": "2017-03-10",
    "extractedNumbers": [
      26,
      38,
      42,
      58,
      70
    ],
    "specialNumberExtracted": 5,
    "suggestedNumbers": [
      52,
      70,
      4,
      50,
      62
    ],
    "specialNumberSuggested": 7,
    "matchedCount": 1
  },
  {
    "drawDate": "2017-01-27",
    "extractedNumbers": [
      17,
      37,
      53,
      54,
      61
    ],
    "specialNumberExtracted": 8,
    "suggestedNumbers": [
      52,
      70,
      4,
      50,
      61
    ],
    "specialNumberSuggested": 4,
    "matchedCount": 1
  },
  {
    "drawDate": "2017-01-17",
    "extractedNumbers": [
      20,
      31,
      54,
      56,
      59
    ],
    "specialNumberExtracted": 3,
    "suggestedNumbers": [
      52,
      70,
      56,
      4,
      50
    ],
    "specialNumberSuggested": 4,
    "matchedCount": 1
  },
  {
    "drawDate": "2016-12-27",
    "extractedNumbers": [
      2,
      28,
      30,
      38,
      39
    ],
    "specialNumberExtracted": 11,
    "suggestedNumbers": [
      20,
      52,
      11,
      28,
      70
    ],
    "specialNumberSuggested": 4,
    "matchedCount": 1
  },
  {
    "drawDate": "2016-12-20",
    "extractedNumbers": [
      1,
      12,
      14,
      48,
      65
    ],
    "specialNumberExtracted": 2,
    "suggestedNumbers": [
      14,
      20,
      52,
      11,
      28
    ],
    "specialNumberSuggested": 4,
    "matchedCount": 1
  },
  {
    "drawDate": "2016-12-09",
    "extractedNumbers": [
      19,
      27,
      47,
      67,
      68
    ],
    "specialNumberExtracted": 1,
    "suggestedNumbers": [
      68,
      14,
      26,
      20,
      52
    ],
    "specialNumberSuggested": 4,
    "matchedCount": 1
  },
  {
    "drawDate": "2016-12-02",
    "extractedNumbers": [
      3,
      33,
      35,
      49,
      51
    ],
    "specialNumberExtracted": 1,
    "suggestedNumbers": [
      68,
      14,
      3,
      26,
      20
    ],
    "specialNumberSuggested": 4,
    "matchedCount": 1
  },
  {
    "drawDate": "2016-11-29",
    "extractedNumbers": [
      22,
      33,
      49,
      51,
      59
    ],
    "specialNumberExtracted": 8,
    "suggestedNumbers": [
      33,
      68,
      14,
      3,
      26
    ],
    "specialNumberSuggested": 8,
    "matchedCount": 1
  },
  {
    "drawDate": "2016-11-04",
    "extractedNumbers": [
      10,
      29,
      32,
      44,
      46
    ],
    "specialNumberExtracted": 10,
    "suggestedNumbers": [
      28,
      36,
      54,
      44,
      38
    ],
    "specialNumberSuggested": 15,
    "matchedCount": 1
  },
  {
    "drawDate": "2016-11-01",
    "extractedNumbers": [
      19,
      24,
      31,
      39,
      45
    ],
    "specialNumberExtracted": 13,
    "suggestedNumbers": [
      36,
      54,
      44,
      19,
      38
    ],
    "specialNumberSuggested": 15,
    "matchedCount": 1
  },
  {
    "drawDate": "2016-10-28",
    "extractedNumbers": [
      7,
      38,
      46,
      57,
      66
    ],
    "specialNumberExtracted": 2,
    "suggestedNumbers": [
      54,
      44,
      19,
      11,
      46
    ],
    "specialNumberSuggested": 15,
    "matchedCount": 1
  },
  {
    "drawDate": "2016-10-21",
    "extractedNumbers": [
      12,
      43,
      44,
      48,
      66
    ],
    "specialNumberExtracted": 3,
    "suggestedNumbers": [
      66,
      19,
      11,
      46,
      21
    ],
    "specialNumberSuggested": 15,
    "matchedCount": 1
  },
  {
    "drawDate": "2016-10-11",
    "extractedNumbers": [
      36,
      39,
      42,
      45,
      48
    ],
    "specialNumberExtracted": 3,
    "suggestedNumbers": [
      19,
      11,
      46,
      21,
      36
    ],
    "specialNumberSuggested": 15,
    "matchedCount": 1
  },
  {
    "drawDate": "2016-10-04",
    "extractedNumbers": [
      18,
      29,
      30,
      54,
      66
    ],
    "specialNumberExtracted": 1,
    "suggestedNumbers": [
      46,
      21,
      36,
      20,
      54
    ],
    "specialNumberSuggested": 15,
    "matchedCount": 1
  },
  {
    "drawDate": "2016-09-16",
    "extractedNumbers": [
      13,
      21,
      28,
      34,
      40
    ],
    "specialNumberExtracted": 15,
    "suggestedNumbers": [
      28,
      36,
      20,
      54,
      66
    ],
    "specialNumberSuggested": 4,
    "matchedCount": 1
  },
  {
    "drawDate": "2016-09-09",
    "extractedNumbers": [
      1,
      34,
      43,
      44,
      63
    ],
    "specialNumberExtracted": 11,
    "suggestedNumbers": [
      36,
      20,
      54,
      66,
      34
    ],
    "specialNumberSuggested": 4,
    "matchedCount": 1
  },
  {
    "drawDate": "2016-09-02",
    "extractedNumbers": [
      22,
      28,
      41,
      46,
      60
    ],
    "specialNumberExtracted": 3,
    "suggestedNumbers": [
      54,
      66,
      34,
      38,
      46
    ],
    "specialNumberSuggested": 4,
    "matchedCount": 1
  },
  {
    "drawDate": "2016-08-26",
    "extractedNumbers": [
      10,
      11,
      31,
      41,
      44
    ],
    "specialNumberExtracted": 14,
    "suggestedNumbers": [
      66,
      34,
      38,
      11,
      46
    ],
    "specialNumberSuggested": 4,
    "matchedCount": 1
  },
  {
    "drawDate": "2016-08-12",
    "extractedNumbers": [
      4,
      41,
      44,
      56,
      69
    ],
    "specialNumberExtracted": 10,
    "suggestedNumbers": [
      38,
      11,
      49,
      28,
      41
    ],
    "specialNumberSuggested": 4,
    "matchedCount": 1
  },
  {
    "drawDate": "2016-08-09",
    "extractedNumbers": [
      12,
      19,
      20,
      44,
      66
    ],
    "specialNumberExtracted": 1,
    "suggestedNumbers": [
      11,
      49,
      28,
      41,
      20
    ],
    "specialNumberSuggested": 4,
    "matchedCount": 1
  },
  {
    "drawDate": "2016-07-19",
    "extractedNumbers": [
      3,
      34,
      54,
      65,
      66
    ],
    "specialNumberExtracted": 4,
    "suggestedNumbers": [
      68,
      6,
      19,
      34,
      11
    ],
    "specialNumberSuggested": 15,
    "matchedCount": 1
  },
  {
    "drawDate": "2016-06-10",
    "extractedNumbers": [
      34,
      61,
      66,
      67,
      68
    ],
    "specialNumberExtracted": 7,
    "suggestedNumbers": [
      41,
      34,
      70,
      11,
      46
    ],
    "specialNumberSuggested": 2,
    "matchedCount": 1
  },
  {
    "drawDate": "2016-05-31",
    "extractedNumbers": [
      9,
      31,
      34,
      41,
      49
    ],
    "specialNumberExtracted": 8,
    "suggestedNumbers": [
      70,
      11,
      46,
      41,
      45
    ],
    "specialNumberSuggested": 2,
    "matchedCount": 1
  },
  {
    "drawDate": "2016-05-20",
    "extractedNumbers": [
      19,
      24,
      26,
      40,
      68
    ],
    "specialNumberExtracted": 8,
    "suggestedNumbers": [
      46,
      40,
      45,
      57,
      21
    ],
    "specialNumberSuggested": 2,
    "matchedCount": 1
  },
  {
    "drawDate": "2016-05-03",
    "extractedNumbers": [
      28,
      29,
      33,
      36,
      45
    ],
    "specialNumberExtracted": 15,
    "suggestedNumbers": [
      33,
      40,
      57,
      6,
      34
    ],
    "specialNumberSuggested": 5,
    "matchedCount": 1
  },
  {
    "drawDate": "2016-04-26",
    "extractedNumbers": [
      14,
      16,
      17,
      28,
      48
    ],
    "specialNumberExtracted": 2,
    "suggestedNumbers": [
      40,
      28,
      57,
      6,
      34
    ],
    "specialNumberSuggested": 12,
    "matchedCount": 1
  },
  {
    "drawDate": "2016-04-22",
    "extractedNumbers": [
      2,
      19,
      21,
      42,
      60
    ],
    "specialNumberExtracted": 13,
    "suggestedNumbers": [
      28,
      57,
      6,
      19,
      34
    ],
    "specialNumberSuggested": 12,
    "matchedCount": 1
  },
  {
    "drawDate": "2016-04-12",
    "extractedNumbers": [
      7,
      11,
      59,
      62,
      63
    ],
    "specialNumberExtracted": 3,
    "suggestedNumbers": [
      34,
      70,
      4,
      11,
      12
    ],
    "specialNumberSuggested": 12,
    "matchedCount": 1
  },
  {
    "drawDate": "2016-03-29",
    "extractedNumbers": [
      33,
      38,
      40,
      46,
      49
    ],
    "specialNumberExtracted": 15,
    "suggestedNumbers": [
      4,
      11,
      12,
      35,
      46
    ],
    "specialNumberSuggested": 11,
    "matchedCount": 1
  },
  {
    "drawDate": "2016-03-22",
    "extractedNumbers": [
      6,
      19,
      34,
      38,
      70
    ],
    "specialNumberExtracted": 5,
    "suggestedNumbers": [
      3,
      38,
      42,
      24,
      46
    ],
    "specialNumberSuggested": 9,
    "matchedCount": 1
  }
]